logutil/__init__.py
logutil/src/__init__.py
logutil/src/init_logging.py
logutil/src/init_loguru.py
logutil-0.1.11.dist-info/LICENSE
logutil-0.1.11.dist-info/METADATA
logutil-0.1.11.dist-info/WHEEL
logutil-0.1.11.dist-info/RECORD
