Metadata-Version: 2.3
Name: logutil
Version: 0.1.11
Summary: Easy initialization of standard python logging and loguru
License: Apache-2.0
Author: Mysterious Ben
Author-email: datascience@tuta.io
Requires-Python: >=3.10,<4.0
Classifier: License :: OSI Approved :: Apache Software License
Classifier: Programming Language :: Python :: 3
Classifier: Programming Language :: Python :: 3.10
Classifier: Programming Language :: Python :: 3.11
Classifier: Programming Language :: Python :: 3.12
Classifier: Programming Language :: Python :: 3.13
Provides-Extra: all
Provides-Extra: loguru
Provides-Extra: notifiers
Requires-Dist: loguru (>=0.7) ; extra == "loguru" or extra == "all"
Requires-Dist: notifiers (>=1.2,<2.0) ; extra == "notifiers" or extra == "all"
Requires-Dist: sentry-sdk (>=1.3,<2.0) ; extra == "notifiers" or extra == "all"
